polite/__init__.py
polite/polite.py
polite-1.0.1.dist-info/LICENSE
polite-1.0.1.dist-info/METADATA
polite-1.0.1.dist-info/WHEEL
polite-1.0.1.dist-info/top_level.txt
polite-1.0.1.dist-info/RECORD
