Metadata-Version: 2.1
Name: polite
Version: 1.0.1
Summary: Module that helps you being less rude while coding
Home-page: https://github.com/fleskovar/polite
Download-URL: https://github.com/fleskovar/polite/releases/download/v1.0.1/polite-1.0.1.tar.gz
Author: Francisco Leskovar
Author-email: francisco.leskovar@gmail.com
Classifier: Programming Language :: Python :: 3
Classifier: License :: OSI Approved :: MIT License
License-File: LICENSE
